fme_packager/__init__.py
fme_packager/__main__.py
fme_packager/cli.py
fme_packager/exception.py
fme_packager/fme_env.py
fme_packager/help.py
fme_packager/metadata.py
fme_packager/operations.py
fme_packager/packager.py
fme_packager/spec.json
fme_packager/summarizer.py
fme_packager/summarizer_spec.json
fme_packager/transformer.py
fme_packager/verifier.py
fme_packager/web_service.py
fme_packager-1.18.2.dist-info/licenses/LICENSE
fme_packager-1.18.2.dist-info/METADATA
fme_packager-1.18.2.dist-info/WHEEL
fme_packager-1.18.2.dist-info/entry_points.txt
fme_packager-1.18.2.dist-info/top_level.txt
fme_packager-1.18.2.dist-info/RECORD
