Metadata-Version: 2.4
Name: fme_packager
Version: 1.18.2
Summary: Tool for creating FME Packages.
Home-page: https://github.com/safesoftware/fme-packager
Author: Safe Software Inc.
License: BSD
Keywords: FME fmeobjects
Classifier: Programming Language :: Python :: 3
Classifier: Intended Audience :: Developers
Requires-Python: >=3.9
License-File: LICENSE
Requires-Dist: click>=8.1.6
Requires-Dist: cookiecutter>=2.2.3
Requires-Dist: jsonschema==4.17.3; python_version < "3.11"
Requires-Dist: jsonschema>=4.25.1; python_version >= "3.11"
Requires-Dist: pypng>=0.20220715.0
Requires-Dist: ruamel.yaml>=0.17.32
Requires-Dist: xmltodict>=0.13.0
Requires-Dist: packaging>=23.1
Requires-Dist: build>=0.10.0
Requires-Dist: wheel>=0.40.0
Requires-Dist: setuptools>=68.0.0
Requires-Dist: markdown>=3.4.3
Provides-Extra: dev
Requires-Dist: pytest>=8.3.4; extra == "dev"
Requires-Dist: pytest-cov>=6.2.1; extra == "dev"
Requires-Dist: pytest-mock>=3.14.0; extra == "dev"
Requires-Dist: coverage[toml]>=7.6.10; extra == "dev"
Requires-Dist: ruff>=0.9.4; extra == "dev"
Requires-Dist: tox>=4.16.0; extra == "dev"
Dynamic: license-file
